weatherapp/__init__.py
weatherapp/weather.py
weatherapp/weather_api.py
weatherapp/model/__init__.py
weatherapp/model/forecast_request.py
weatherapp/model/forecast_response.py
weatherapp/model/historical_request.py
weatherapp/model/historical_response.py
burane_weather_app_20_11_2024-0.4.0.dist-info/METADATA
burane_weather_app_20_11_2024-0.4.0.dist-info/WHEEL
burane_weather_app_20_11_2024-0.4.0.dist-info/top_level.txt
burane_weather_app_20_11_2024-0.4.0.dist-info/RECORD
