Metadata-Version: 2.1
Name: burane-weather-app-20-11-2024
Version: 0.4.0
Summary: application météo
Home-page: https://github.com/Burane/WeatherApp.git
Author: Antoine
Author-email: antoine.kerbiriou@sinay.fr
Classifier: Programming Language :: Python :: 3
Classifier: License :: OSI Approved :: MIT License
Classifier: Operating System :: OS Independent
Requires-Python: >=3.6
Requires-Dist: requests
